Metadata-Version: 2.1
Name: khmerpronounce
Version: 0.0.1
Summary: Khmer Pronounciation Toolkit
Home-page: https://github.com/seanghay/khmerpronounce
Author: Seanghay Yath
Author-email: seanghay.dev@gmail.com
License: Apache License 2.0
Platform: UNKNOWN
Classifier: Programming Language :: Python :: 3
Classifier: Operating System :: OS Independent
Classifier: Intended Audience :: Developers
Classifier: Natural Language :: English
Requires-Python: >3.5
